LICENSE
README.md
setup.py
lexica/__init__.py
lexica/constants.py
lexica/core.py
lexica/core_async.py
lexica/utils.py
lexica_api.egg-info/PKG-INFO
lexica_api.egg-info/SOURCES.txt
lexica_api.egg-info/dependency_links.txt
lexica_api.egg-info/requires.txt
lexica_api.egg-info/top_level.txt