Metadata-Version: 2.1
Name: lexica-api
Version: 1.5.6
Summary: The python package for api.qewertyy.me
Home-page: https://github.com/Qewertyy/LexicaAPI
Author: Qewertyy
Author-email: Qewertyy.irl@gmail.com
Keywords: Python,API,Bard,Google Bard,Large Language Model,Chatbot API,Google API,Chatbot,Image Generations,Latent Diffusion,State of Art,Image Reverse Search,Reverse Image Search
Classifier: Programming Language :: Python
Classifier: Programming Language :: Python :: 3.7
Classifier: Programming Language :: Python :: 3.8
Requires-Python: >=3.8
License-File: LICENSE
